adfoc/focal_mechanism_svm.py
ADFoc-0.1.1.dist-info/METADATA
ADFoc-0.1.1.dist-info/WHEEL
ADFoc-0.1.1.dist-info/top_level.txt
ADFoc-0.1.1.dist-info/RECORD
