Metadata-Version: 2.2
Name: ADFoc
Version: 0.1.1
Requires-Dist: numpy
Requires-Dist: h5py
Requires-Dist: matplotlib
Requires-Dist: pandas
Dynamic: description-content-type
Dynamic: requires-dist
